upycli/__init__.py
upycli/decorator.py
upycli/runner.py
upycli/types.py
upycli-0.2.11.dist-info/METADATA
upycli-0.2.11.dist-info/WHEEL
upycli-0.2.11.dist-info/entry_points.txt
upycli-0.2.11.dist-info/top_level.txt
upycli-0.2.11.dist-info/RECORD
