Metadata-Version: 2.1
Name: upycli
Version: 0.2.11
Summary: A microscopic library to turn any function into a CLI.
Home-page: https://github.com/zrthxn/uPyCLI
Maintainer: Alisamar Husian
Maintainer-email: zrthxn@gmail.com
